<?xml version='1.0' encoding='utf-8'?>
<q:quakeml xmlns="http://quakeml.org/xmlns/bed/1.2" xmlns:q="http://quakeml.org/xmlns/quakeml/1.2">
  <eventParameters publicID="smi:local/a2c56414-239b-4a14-ae41-f4e00bd21dd0">
    <event publicID="smi:local/ndk/C201810292326A/event">
      <preferredOriginID>smi:local/ndk/C201810292326A/origin#cmtorigin</preferredOriginID>
      <preferredMagnitudeID>smi:local/ndk/C201810292326A/magnitude#moment_mag</preferredMagnitudeID>
      <preferredFocalMechanismID>smi:local/ndk/C201810292326A/focal_mechanism</preferredFocalMechanismID>
      <type>earthquake</type>
      <typeCertainty>known</typeCertainty>
      <description>
        <text>CENTRAL EAST PACIFIC RISE</text>
        <type>Flinn-Engdahl region</type>
      </description>
      <description>
        <text>C201810292326A</text>
        <type>earthquake name</type>
      </description>
      <origin publicID="smi:local/ndk/C201810292326A/origin#reforigin">
        <time>
          <value>2018-10-29T23:26:09.000000Z</value>
        </time>
        <latitude>
          <value>-4.57</value>
        </latitude>
        <longitude>
          <value>-105.92</value>
        </longitude>
        <depth>
          <value>10000.0</value>
        </depth>
        <type>hypocenter</type>
        <comment id="smi:local/ndk/C201810292326A/comment#ref_origin">
          <text>Hypocenter catalog: PDEW</text>
        </comment>
      </origin>
      <origin publicID="smi:local/ndk/C201810292326A/origin#cmtorigin">
        <time>
          <value>2018-10-29T23:26:10.400000Z</value>
          <uncertainty>0.1</uncertainty>
        </time>
        <latitude>
          <value>-4.42</value>
          <uncertainty>0.0</uncertainty>
        </latitude>
        <longitude>
          <value>-105.96</value>
          <uncertainty>0.0</uncertainty>
        </longitude>
        <depth>
          <value>14100.0</value>
          <uncertainty>400.0</uncertainty>
        </depth>
        <depthType>from moment tensor inversion</depthType>
        <timeFixed>false</timeFixed>
        <epicenterFixed>false</epicenterFixed>
        <type>centroid</type>
        <creationInfo>
          <agencyID>GCMT</agencyID>
          <version>V10</version>
        </creationInfo>
      </origin>
      <magnitude publicID="smi:local/ndk/C201810292326A/magnitude#moment_mag">
        <mag>
          <value>5.88</value>
        </mag>
        <type>Mwc</type>
        <originID>smi:local/ndk/C201810292326A/origin#cmtorigin</originID>
        <creationInfo>
          <agencyID>GCMT</agencyID>
          <version>V10</version>
        </creationInfo>
      </magnitude>
      <magnitude publicID="smi:local/ndk/C201810292326A/magnitude#mb">
        <mag>
          <value>0.0</value>
        </mag>
        <type>mb</type>
        <comment id="smi:local/ndk/C201810292326A/comment#mb_magnitude">
          <text>Reported magnitude in NDK file. Most likely 'mb'.</text>
        </comment>
      </magnitude>
      <magnitude publicID="smi:local/ndk/C201810292326A/magnitude#MS">
        <mag>
          <value>5.8</value>
        </mag>
        <type>MS</type>
        <comment id="smi:local/ndk/C201810292326A/comment#MS_magnitude">
          <text>Reported magnitude in NDK file. Most likely 'MS'.</text>
        </comment>
      </magnitude>
      <focalMechanism publicID="smi:local/ndk/C201810292326A/focal_mechanism">
        <nodalPlanes>
          <nodalPlane1>
            <strike>
              <value>100.0</value>
            </strike>
            <dip>
              <value>82.0</value>
            </dip>
            <rake>
              <value>-2.0</value>
            </rake>
          </nodalPlane1>
          <nodalPlane2>
            <strike>
              <value>190.0</value>
            </strike>
            <dip>
              <value>88.0</value>
            </dip>
            <rake>
              <value>-172.0</value>
            </rake>
          </nodalPlane2>
        </nodalPlanes>
        <principalAxes>
          <tAxis>
            <azimuth>
              <value>325.0</value>
            </azimuth>
            <plunge>
              <value>4.0</value>
            </plunge>
            <length>
              <value>8.25e+17</value>
            </length>
          </tAxis>
          <pAxis>
            <azimuth>
              <value>55.0</value>
            </azimuth>
            <plunge>
              <value>7.0</value>
            </plunge>
            <length>
              <value>-8.379e+17</value>
            </length>
          </pAxis>
          <nAxis>
            <azimuth>
              <value>204.0</value>
            </azimuth>
            <plunge>
              <value>82.0</value>
            </plunge>
            <length>
              <value>1.33e+16</value>
            </length>
          </nAxis>
        </principalAxes>
        <momentTensor publicID="smi:local/ndk/C201810292326A/momenttensor">
          <derivedOriginID>smi:local/ndk/C201810292326A/origin#cmtorigin</derivedOriginID>
          <dataUsed>
            <waveType>body waves</waveType>
            <stationCount>157</stationCount>
            <componentCount>331</componentCount>
            <shortestPeriod>40.0</shortestPeriod>
          </dataUsed>
          <dataUsed>
            <waveType>surface waves</waveType>
            <stationCount>165</stationCount>
            <componentCount>362</componentCount>
            <shortestPeriod>50.0</shortestPeriod>
          </dataUsed>
          <dataUsed>
            <waveType>mantle waves</waveType>
            <stationCount>128</stationCount>
            <componentCount>173</componentCount>
            <shortestPeriod>125.0</shortestPeriod>
          </dataUsed>
          <scalarMoment>
            <value>8.315e+17</value>
          </scalarMoment>
          <tensor>
            <Mrr>
              <value>5500000000000000.0</value>
              <uncertainty>4300000000000000.0</uncertainty>
            </Mrr>
            <Mtt>
              <value>2.81e+17</value>
              <uncertainty>4800000000000000.0</uncertainty>
            </Mtt>
            <Mpp>
              <value>-2.86e+17</value>
              <uncertainty>5300000000000000.0</uncertainty>
            </Mpp>
            <Mrt>
              <value>-9900000000000000.0</value>
              <uncertainty>9400000000000000.0</uncertainty>
            </Mrt>
            <Mrp>
              <value>1.16e+17</value>
              <uncertainty>1.08e+16</uncertainty>
            </Mrp>
            <Mtp>
              <value>7.73e+17</value>
              <uncertainty>4900000000000000.0</uncertainty>
            </Mtp>
          </tensor>
          <sourceTimeFunction>
            <type>triangle</type>
            <duration>4.2</duration>
          </sourceTimeFunction>
          <inversionType>zero trace</inversionType>
          <creationInfo>
            <agencyID>GCMT</agencyID>
            <version>V10</version>
          </creationInfo>
        </momentTensor>
        <comment id="smi:local/ndk/C201810292326A/comment#cmt_type">
          <text>CMT Analysis Type: Standard</text>
        </comment>
        <comment id="smi:local/ndk/C201810292326A/comment#cmt_timestamp">
          <text>CMT Timestamp: S-20181230023631</text>
        </comment>
        <creationInfo>
          <agencyID>GCMT</agencyID>
          <version>V10</version>
        </creationInfo>
      </focalMechanism>
    </event>
  </eventParameters>
</q:quakeml>
